__init__.py
dataloader/__init__.py
dataloader/_base.py
dataloader/jsonl_reader.py
exporter/__init__.py
modelling/__init__.py
modelling/_base.py
modelling/common/__init__.py
modelling/common/attn_utils.py
modelling/common/config_module.py
modelling/common/conv.py
modelling/image/diffusion/diffusion.py
modelling/language/_base.py
modelling/language/output.py
modelling/language/gpt2/gpt2_config.py
modelling/language/gpt2/gpt2_model.py
modelling/language/gpt_neox/__init__.py
modelling/language/gptj/__init__.py
modelling/language/gptj/gptj_config.py
modelling/language/gptj/gptj_model.py
modelling/language/llama/llama_config.py
modelling/language/llama/llama_model.py
modelling/language/llama/llama_tokenizer.py
modelling/language/opt/__init__.py
modelling/language/roberta/__init__.py
modelling/language/tokenizers/hf_tokenizer.py
modelling/utils/jax_utils.py
nn/losses.py
nn/optimizers.py
parallelism/device.py
parallelism/partition.py
parallelism/utils.py
profiler/__init__.py
trainer/__init__.py
trainer/_base.py
trainer/hyperparams.py
trainer/trainer.py
utils/global_norm.py
utils/gradient_checkpoint.py
utils/rng.py
utils/trees.py
fmengine-0.0.1.dist-info/LICENSE
fmengine-0.0.1.dist-info/METADATA
fmengine-0.0.1.dist-info/WHEEL
fmengine-0.0.1.dist-info/top_level.txt
fmengine-0.0.1.dist-info/RECORD
